{"modes":{"drought_n":{"x":-600,"source":"https://github.com/26F-Studio/Techmino/tree/main/parts/modes/drought_n.lua","name":"drought_n","y":400,"icon":"drought","shape":1,"unlock":["drought_l"],"size":40},"strategy_e_plus":{"x":-300,"source":"https://github.com/26F-Studio/Techmino/tree/main/parts/modes/strategy_e_plus.lua","name":"strategy_e_plus","y":-1120,"icon":"master","shape":3,"unlock":[],"size":40},"sprint_20l":{"x":-200,"source":"https://github.com/26F-Studio/Techmino/tree/main/parts/modes/sprint_20l.lua","name":"sprint_20l","y":200,"icon":"sprint1","shape":1,"unlock":[],"size":50},"round_u":{"x":-1400,"source":"https://github.com/26F-Studio/Techmino/tree/main/parts/modes/round_u.lua","name":"round_u","y":-800,"icon":"round","shape":1,"unlock":[],"size":40},"survivor_u":{"x":1250,"source":"https://github.com/26F-Studio/Techmino/tree/main/parts/modes/survivor_u.lua","name":"survivor_u","y":-600,"icon":"survivor","shape":2,"unlock":[],"size":40},"ultra":{"x":-1400,"source":"https://github.com/26F-Studio/Techmino/tree/main/parts/modes/ultra.lua","name":"ultra","y":-600,"icon":"ultra","shape":1,"unlock":[],"size":40},"pc_inf":{"x":1100,"source":"https://github.com/26F-Studio/Techmino/tree/main/parts/modes/pc_inf.lua","name":"pc_inf","y":-280,"icon":"pc","shape":2,"unlock":[],"size":40},"dig_u":{"x":850,"source":"https://github.com/26F-Studio/Techmino/tree/main/parts/modes/dig_u.lua","name":"dig_u","y":-1000,"icon":"dig","shape":1,"unlock":[],"size":40},"sprint_40l":{"x":0,"source":"https://github.com/26F-Studio/Techmino/tree/main/parts/modes/sprint_40l.lua","name":"sprint_40l","y":-300,"icon":"sprint2","shape":1,"unlock":["dig_10l","sprint_100l","marathon_n","sprintPenta","sprintMPH","sprint123"],"size":40},"blind_n":{"x":150,"source":"https://github.com/26F-Studio/Techmino/tree/main/parts/modes/blind_n.lua","name":"blind_n","y":-800,"icon":"hidden2","shape":1,"unlock":["blind_h"],"size":40},"tech_l":{"x":400,"source":"https://github.com/26F-Studio/Techmino/tree/main/parts/modes/tech_l.lua","name":"tech_l","y":320,"icon":"tech","shape":1,"unlock":["tech_l_plus"],"size":40},"blind_l":{"x":150,"source":"https://github.com/26F-Studio/Techmino/tree/main/parts/modes/blind_l.lua","name":"blind_l","y":-1000,"icon":"hidden4","shape":3,"unlock":["blind_u"],"size":35},"sprint_100l":{"x":-400,"source":"https://github.com/26F-Studio/Techmino/tree/main/parts/modes/sprint_100l.lua","name":"sprint_100l","y":200,"icon":"sprint2","shape":1,"unlock":["sprint_400l","drought_n"],"size":50},"sprint_1000l":{"x":-800,"source":"https://github.com/26F-Studio/Techmino/tree/main/parts/modes/sprint_1000l.lua","name":"sprint_1000l","y":200,"icon":"sprint3","shape":1,"unlock":[],"size":40},"pctrain_l":{"x":900,"source":"https://github.com/26F-Studio/Techmino/tree/main/parts/modes/pctrain_l.lua","name":"pctrain_l","y":-300,"icon":"pc","shape":1,"unlock":[],"size":40},"sprint123":{"x":160,"source":"https://github.com/26F-Studio/Techmino/tree/main/parts/modes/sprint123.lua","name":"sprint123","y":-400,"icon":"sprint_tri","shape":1,"unlock":[],"size":40},"techmino49_u":{"x":-1100,"source":"https://github.com/26F-Studio/Techmino/tree/main/parts/modes/techmino49_u.lua","name":"techmino49_u","y":-1600,"icon":"t49","shape":1,"unlock":[],"size":40},"techmino99_u":{"x":-1300,"source":"https://github.com/26F-Studio/Techmino/tree/main/parts/modes/techmino99_u.lua","name":"techmino99_u","y":-1800,"icon":"t99","shape":1,"unlock":[],"size":40},"survivor_l":{"x":1050,"source":"https://github.com/26F-Studio/Techmino/tree/main/parts/modes/survivor_l.lua","name":"survivor_l","y":-600,"icon":"survivor","shape":3,"unlock":["survivor_u"],"size":40},"construct_sg":{"x":-500,"source":"https://github.com/26F-Studio/Techmino/tree/main/parts/modes/construct_sg.lua","name":"construct_sg","y":-520,"icon":"secret_grade","shape":1,"unlock":["construct_checker"],"size":40},"classic_l":{"x":-400,"source":"https://github.com/26F-Studio/Techmino/tree/main/parts/modes/classic_l.lua","name":"classic_l","y":-1050,"icon":"classic","shape":3,"unlock":["classic_u"],"size":35},"master_ph":{"x":-170,"source":"https://github.com/26F-Studio/Techmino/tree/main/parts/modes/master_ph.lua","name":"master_ph","y":-1450,"icon":"master","shape":2,"unlock":[],"size":40},"big_n":{"x":-400,"source":"https://github.com/26F-Studio/Techmino/tree/main/parts/modes/big_n.lua","name":"big_n","y":-400,"icon":"big","shape":1,"unlock":["big_h"],"size":40},"dig_400l":{"x":-1000,"source":"https://github.com/26F-Studio/Techmino/tree/main/parts/modes/dig_400l.lua","name":"dig_400l","y":-200,"icon":"dig_sprint","shape":1,"unlock":[],"size":40},"blind_e":{"x":150,"source":"https://github.com/26F-Studio/Techmino/tree/main/parts/modes/blind_e.lua","name":"blind_e","y":-700,"icon":"hidden","shape":1,"unlock":["blind_n","master_instinct"],"size":40},"solo_l":{"x":-1200,"source":"https://github.com/26F-Studio/Techmino/tree/main/parts/modes/solo_l.lua","name":"solo_l","y":-1000,"icon":"solo","shape":1,"unlock":["solo_u"],"size":40},"infinite_dig":{"x":-1200,"source":"https://github.com/26F-Studio/Techmino/tree/main/parts/modes/infinite_dig.lua","name":"infinite_dig","y":-400,"icon":"dig","shape":1,"unlock":[],"size":40},"pc_n":{"x":800,"source":"https://github.com/26F-Studio/Techmino/tree/main/parts/modes/pc_n.lua","name":"pc_n","y":-140,"icon":"pc","shape":1,"unlock":["pc_h"],"size":40},"tech_h_plus":{"x":200,"source":"https://github.com/26F-Studio/Techmino/tree/main/parts/modes/tech_h_plus.lua","name":"tech_h_plus","y":140,"icon":"tech_plus","shape":3,"unlock":[],"size":35},"big_h":{"x":-600,"source":"https://github.com/26F-Studio/Techmino/tree/main/parts/modes/big_h.lua","name":"big_h","y":-400,"icon":"big","shape":1,"unlock":[],"size":40},"infinite":{"x":-1400,"source":"https://github.com/26F-Studio/Techmino/tree/main/parts/modes/infinite.lua","name":"infinite","y":-400,"icon":"infinite","shape":1,"unlock":[],"size":40},"survivor_h":{"x":850,"source":"https://github.com/26F-Studio/Techmino/tree/main/parts/modes/survivor_h.lua","name":"survivor_h","y":-600,"icon":"survivor","shape":1,"unlock":["survivor_l"],"size":40},"dig_eff_400l":{"x":-1200,"source":"https://github.com/26F-Studio/Techmino/tree/main/parts/modes/dig_eff_400l.lua","name":"dig_eff_400l","y":0,"icon":"dig_eff","shape":1,"unlock":[],"size":40},"zen":{"x":-1200,"source":"https://github.com/26F-Studio/Techmino/tree/main/parts/modes/zen.lua","name":"zen","y":-600,"icon":"zen","shape":1,"unlock":["ultra","infinite","infinite_dig","marathon_inf"],"size":40},"master_final":{"x":-100,"source":"https://github.com/26F-Studio/Techmino/tree/main/parts/modes/master_final.lua","name":"master_final","y":-1550,"icon":"master","shape":2,"unlock":[],"size":40},"techmino99_e":{"x":-1300,"source":"https://github.com/26F-Studio/Techmino/tree/main/parts/modes/techmino99_e.lua","name":"techmino99_e","y":-1400,"icon":"t99","shape":1,"unlock":["techmino99_h"],"size":40},"backfire_u":{"x":1070,"source":"https://github.com/26F-Studio/Techmino/tree/main/parts/modes/backfire_u.lua","name":"backfire_u","y":300,"icon":"backfire","shape":2,"unlock":[],"size":35},"pctrain_n":{"x":700,"source":"https://github.com/26F-Studio/Techmino/tree/main/parts/modes/pctrain_n.lua","name":"pctrain_n","y":-300,"icon":"pc","shape":1,"unlock":["pctrain_l","pc_n"],"size":40},"strategy_u":{"x":-150,"source":"https://github.com/26F-Studio/Techmino/tree/main/parts/modes/strategy_u.lua","name":"strategy_u","y":-1280,"icon":"master","shape":2,"unlock":["strategy_u_plus"],"size":30},"backfire_l":{"x":930,"source":"https://github.com/26F-Studio/Techmino/tree/main/parts/modes/backfire_l.lua","name":"backfire_l","y":300,"icon":"backfire","shape":3,"unlock":["backfire_u"],"size":40},"dig_eff_10l":{"x":-600,"source":"https://github.com/26F-Studio/Techmino/tree/main/parts/modes/dig_eff_10l.lua","name":"dig_eff_10l","y":0,"icon":"dig_eff","shape":1,"unlock":["dig_eff_40l"],"size":40},"backfire_n":{"x":640,"source":"https://github.com/26F-Studio/Techmino/tree/main/parts/modes/backfire_n.lua","name":"backfire_n","y":270,"icon":"backfire","shape":1,"unlock":["backfire_h"],"size":40},"dig_10l":{"x":-400,"source":"https://github.com/26F-Studio/Techmino/tree/main/parts/modes/dig_10l.lua","name":"dig_10l","y":-200,"icon":"dig_sprint","shape":1,"unlock":["dig_40l","dig_eff_10l"],"size":40},"tsd_u":{"x":1050,"source":"https://github.com/26F-Studio/Techmino/tree/main/parts/modes/tsd_u.lua","name":"tsd_u","y":170,"icon":"tsd","shape":1,"unlock":[],"size":40},"survivor_n":{"x":650,"source":"https://github.com/26F-Studio/Techmino/tree/main/parts/modes/survivor_n.lua","name":"survivor_n","y":-600,"icon":"survivor","shape":1,"unlock":["survivor_h","attacker_h","defender_n","dig_h"],"size":40},"tech_finesse_f":{"x":1050,"source":"https://github.com/26F-Studio/Techmino/tree/main/parts/modes/tech_finesse_f.lua","name":"tech_finesse_f","y":20,"icon":"tech_plus","shape":1,"unlock":[],"size":40},"tsd_e":{"x":700,"source":"https://github.com/26F-Studio/Techmino/tree/main/parts/modes/tsd_e.lua","name":"tsd_e","y":100,"icon":"tsd","shape":1,"unlock":["tsd_h"],"size":40},"drought_l":{"x":-800,"source":"https://github.com/26F-Studio/Techmino/tree/main/parts/modes/drought_l.lua","name":"drought_l","y":400,"icon":"drought","shape":1,"unlock":[],"size":40},"master_ex":{"x":170,"source":"https://github.com/26F-Studio/Techmino/tree/main/parts/modes/master_ex.lua","name":"master_ex","y":-1450,"icon":"master_ex","shape":2,"unlock":[],"size":40},"tech_finesse":{"x":850,"source":"https://github.com/26F-Studio/Techmino/tree/main/parts/modes/tech_finesse.lua","name":"tech_finesse","y":20,"icon":"tech","shape":1,"unlock":["tech_finesse_f"],"size":40},"dig_eff_100l":{"x":-1000,"source":"https://github.com/26F-Studio/Techmino/tree/main/parts/modes/dig_eff_100l.lua","name":"dig_eff_100l","y":0,"icon":"dig_eff","shape":1,"unlock":["dig_eff_400l"],"size":40},"tech_l_plus":{"x":200,"source":"https://github.com/26F-Studio/Techmino/tree/main/parts/modes/tech_l_plus.lua","name":"tech_l_plus","y":290,"icon":"tech_plus","shape":3,"unlock":[],"size":35},"master_m":{"x":100,"source":"https://github.com/26F-Studio/Techmino/tree/main/parts/modes/master_m.lua","name":"master_m","y":-1550,"icon":"master","shape":2,"unlock":[],"size":40},"tech_h":{"x":400,"source":"https://github.com/26F-Studio/Techmino/tree/main/parts/modes/tech_h.lua","name":"tech_h","y":170,"icon":"tech","shape":1,"unlock":["tech_h_plus","tech_l"],"size":40},"classic_h":{"x":-300,"source":"https://github.com/26F-Studio/Techmino/tree/main/parts/modes/classic_h.lua","name":"classic_h","y":-950,"icon":"classic","shape":3,"unlock":["classic_l"],"size":40},"tech_n":{"x":400,"source":"https://github.com/26F-Studio/Techmino/tree/main/parts/modes/tech_n.lua","name":"tech_n","y":20,"icon":"tech","shape":1,"unlock":["tech_n_plus","tech_h"],"size":40},"construct_checker":{"x":-700,"source":"https://github.com/26F-Studio/Techmino/tree/main/parts/modes/construct_checker.lua","name":"construct_checker","y":-520,"icon":"secret_grade","shape":3,"unlock":["construct_invsg"],"size":40},"sprintMPH":{"x":200,"source":"https://github.com/26F-Studio/Techmino/tree/main/parts/modes/sprintMPH.lua","name":"sprintMPH","y":-260,"icon":"sprint2","shape":3,"unlock":[],"size":40},"round_h":{"x":-1000,"source":"https://github.com/26F-Studio/Techmino/tree/main/parts/modes/round_h.lua","name":"round_h","y":-800,"icon":"round","shape":1,"unlock":["round_l"],"size":40},"sprintEff":{"x":360,"source":"https://github.com/26F-Studio/Techmino/tree/main/parts/modes/sprintEff.lua","name":"sprintEff","y":-150,"icon":"sprint2","shape":1,"unlock":[],"size":40},"sprintAtk":{"x":500,"source":"https://github.com/26F-Studio/Techmino/tree/main/parts/modes/sprintAtk.lua","name":"sprintAtk","y":-280,"icon":"sprint2","shape":1,"unlock":["sprintEff","tech_n","tech_finesse","tsd_e","backfire_n"],"size":40},"solo_n":{"x":-800,"source":"https://github.com/26F-Studio/Techmino/tree/main/parts/modes/solo_n.lua","name":"solo_n","y":-1000,"icon":"solo","shape":1,"unlock":["solo_h"],"size":40},"pc_l":{"x":1100,"source":"https://github.com/26F-Studio/Techmino/tree/main/parts/modes/pc_l.lua","name":"pc_l","y":-140,"icon":"pc","shape":3,"unlock":[],"size":40},"dig_40l":{"x":-600,"source":"https://github.com/26F-Studio/Techmino/tree/main/parts/modes/dig_40l.lua","name":"dig_40l","y":-200,"icon":"dig_sprint","shape":1,"unlock":["dig_100l","dig_quad_10l"],"size":40},"techmino49_h":{"x":-1100,"source":"https://github.com/26F-Studio/Techmino/tree/main/parts/modes/techmino49_h.lua","name":"techmino49_h","y":-1400,"icon":"t49","shape":1,"unlock":["techmino49_u"],"size":40},"solo_u":{"x":-1400,"source":"https://github.com/26F-Studio/Techmino/tree/main/parts/modes/solo_u.lua","name":"solo_u","y":-1000,"icon":"solo","shape":1,"unlock":[],"size":40},"construct_invsg":{"x":-900,"source":"https://github.com/26F-Studio/Techmino/tree/main/parts/modes/construct_invsg.lua","name":"construct_invsg","y":-520,"icon":"secret_grade","shape":2,"unlock":[],"size":40},"master_n":{"x":0,"source":"https://github.com/26F-Studio/Techmino/tree/main/parts/modes/master_n.lua","name":"master_n","y":-1000,"icon":"master","shape":1,"unlock":["master_h","strategy_h"],"size":40},"master_h":{"x":0,"source":"https://github.com/26F-Studio/Techmino/tree/main/parts/modes/master_h.lua","name":"master_h","y":-1200,"icon":"master","shape":3,"unlock":["master_final","master_ex","master_ph","master_m","master_g","strategy_u"],"size":40},"c4wtrain_n":{"x":700,"source":"https://github.com/26F-Studio/Techmino/tree/main/parts/modes/c4wtrain_n.lua","name":"c4wtrain_n","y":-450,"icon":"pc","shape":1,"unlock":["c4wtrain_l"],"size":40},"strategy_h_plus":{"x":-300,"source":"https://github.com/26F-Studio/Techmino/tree/main/parts/modes/strategy_h_plus.lua","name":"strategy_h_plus","y":-1250,"icon":"master","shape":3,"unlock":[],"size":35},"defender_l":{"x":650,"source":"https://github.com/26F-Studio/Techmino/tree/main/parts/modes/defender_l.lua","name":"defender_l","y":-1000,"icon":"defend","shape":1,"unlock":[],"size":40},"dig_h":{"x":850,"source":"https://github.com/26F-Studio/Techmino/tree/main/parts/modes/dig_h.lua","name":"dig_h","y":-800,"icon":"dig","shape":1,"unlock":["dig_u"],"size":40},"defender_n":{"x":650,"source":"https://github.com/26F-Studio/Techmino/tree/main/parts/modes/defender_n.lua","name":"defender_n","y":-800,"icon":"defend","shape":1,"unlock":["defender_l"],"size":40},"attacker_u":{"x":450,"source":"https://github.com/26F-Studio/Techmino/tree/main/parts/modes/attacker_u.lua","name":"attacker_u","y":-1000,"icon":"attack","shape":1,"unlock":[],"size":40},"attacker_h":{"x":450,"source":"https://github.com/26F-Studio/Techmino/tree/main/parts/modes/attacker_h.lua","name":"attacker_h","y":-800,"icon":"attack","shape":1,"unlock":["attacker_u"],"size":40},"tsd_h":{"x":860,"source":"https://github.com/26F-Studio/Techmino/tree/main/parts/modes/tsd_h.lua","name":"tsd_h","y":160,"icon":"tsd","shape":1,"unlock":["tsd_u"],"size":40},"survivor_e":{"x":450,"source":"https://github.com/26F-Studio/Techmino/tree/main/parts/modes/survivor_e.lua","name":"survivor_e","y":-600,"icon":"survivor","shape":1,"unlock":["survivor_n"],"size":40},"classic_e":{"x":-200,"source":"https://github.com/26F-Studio/Techmino/tree/main/parts/modes/classic_e.lua","name":"classic_e","y":-850,"icon":"classic","shape":1,"unlock":["classic_h"],"size":40},"techmino49_e":{"x":-1100,"source":"https://github.com/26F-Studio/Techmino/tree/main/parts/modes/techmino49_e.lua","name":"techmino49_e","y":-1200,"icon":"t49","shape":1,"unlock":["techmino49_h","techmino99_e"],"size":40},"classic_u":{"x":-500,"source":"https://github.com/26F-Studio/Techmino/tree/main/parts/modes/classic_u.lua","name":"classic_u","y":-1150,"icon":"classic","shape":2,"unlock":[],"size":30},"sprint_10l":{"x":0,"source":"https://github.com/26F-Studio/Techmino/tree/main/parts/modes/sprint_10l.lua","name":"sprint_10l","y":0,"icon":"sprint1","shape":1,"unlock":["sprint_20l","sprint_40l"],"size":40},"tech_n_plus":{"x":200,"source":"https://github.com/26F-Studio/Techmino/tree/main/parts/modes/tech_n_plus.lua","name":"tech_n_plus","y":-10,"icon":"tech_plus","shape":3,"unlock":[],"size":40},"dig_quad_10l":{"x":-800,"source":"https://github.com/26F-Studio/Techmino/tree/main/parts/modes/dig_quad_10l.lua","name":"dig_quad_10l","y":-400,"icon":"drought","shape":1,"unlock":[],"size":40},"c4wtrain_l":{"x":900,"source":"https://github.com/26F-Studio/Techmino/tree/main/parts/modes/c4wtrain_l.lua","name":"c4wtrain_l","y":-450,"icon":"pc","shape":1,"unlock":[],"size":40},"blind_wtf":{"x":150,"source":"https://github.com/26F-Studio/Techmino/tree/main/parts/modes/blind_wtf.lua","name":"blind_wtf","y":-1200,"icon":"hidden5","shape":2,"unlock":[],"size":25},"sprint_400l":{"x":-600,"source":"https://github.com/26F-Studio/Techmino/tree/main/parts/modes/sprint_400l.lua","name":"sprint_400l","y":200,"icon":"sprint3","shape":1,"unlock":["sprint_1000l"],"size":40},"dig_eff_40l":{"x":-800,"source":"https://github.com/26F-Studio/Techmino/tree/main/parts/modes/dig_eff_40l.lua","name":"dig_eff_40l","y":0,"icon":"dig_eff","shape":1,"unlock":["dig_eff_100l"],"size":40},"sprintPenta":{"x":130,"source":"https://github.com/26F-Studio/Techmino/tree/main/parts/modes/sprintPenta.lua","name":"sprintPenta","y":-140,"icon":"sprint_pento","shape":3,"unlock":[],"size":40},"backfire_h":{"x":790,"source":"https://github.com/26F-Studio/Techmino/tree/main/parts/modes/backfire_h.lua","name":"backfire_h","y":300,"icon":"backfire","shape":1,"unlock":["backfire_l"],"size":40},"master_instinct":{"x":285,"source":"https://github.com/26F-Studio/Techmino/tree/main/parts/modes/master_instinct.lua","name":"master_instinct","y":-835,"icon":"hidden2","shape":3,"unlock":[],"size":40},"marathon_n":{"x":0,"source":"https://github.com/26F-Studio/Techmino/tree/main/parts/modes/marathon_n.lua","name":"marathon_n","y":-600,"icon":"marathon","shape":1,"unlock":["marathon_h","solo_e","round_e","big_n","blind_e","classic_e","survivor_e","c4wtrain_n","pctrain_n","sprintAtk","zen","construct_sg"],"size":60},"marathon_h":{"x":0,"source":"https://github.com/26F-Studio/Techmino/tree/main/parts/modes/marathon_h.lua","name":"marathon_h","y":-800,"icon":"marathon","shape":1,"unlock":["master_n","strategy_e"],"size":50},"blind_h":{"x":150,"source":"https://github.com/26F-Studio/Techmino/tree/main/parts/modes/blind_h.lua","name":"blind_h","y":-900,"icon":"hidden3","shape":1,"unlock":["blind_l"],"size":35},"dig_100l":{"x":-800,"source":"https://github.com/26F-Studio/Techmino/tree/main/parts/modes/dig_100l.lua","name":"dig_100l","y":-200,"icon":"dig_sprint","shape":1,"unlock":["dig_400l"],"size":40},"round_e":{"x":-600,"source":"https://github.com/26F-Studio/Techmino/tree/main/parts/modes/round_e.lua","name":"round_e","y":-800,"icon":"round","shape":1,"unlock":["round_n"],"size":40},"techmino99_h":{"x":-1300,"source":"https://github.com/26F-Studio/Techmino/tree/main/parts/modes/techmino99_h.lua","name":"techmino99_h","y":-1600,"icon":"t99","shape":1,"unlock":["techmino99_u"],"size":40},"round_n":{"x":-800,"source":"https://github.com/26F-Studio/Techmino/tree/main/parts/modes/round_n.lua","name":"round_n","y":-800,"icon":"round","shape":1,"unlock":["round_h"],"size":40},"pc_h":{"x":950,"source":"https://github.com/26F-Studio/Techmino/tree/main/parts/modes/pc_h.lua","name":"pc_h","y":-140,"icon":"pc","shape":3,"unlock":["pc_l","pc_inf"],"size":40},"round_l":{"x":-1200,"source":"https://github.com/26F-Studio/Techmino/tree/main/parts/modes/round_l.lua","name":"round_l","y":-800,"icon":"round","shape":1,"unlock":["round_u"],"size":40},"master_g":{"x":0,"source":"https://github.com/26F-Studio/Techmino/tree/main/parts/modes/master_g.lua","name":"master_g","y":-1600,"icon":"master","shape":3,"unlock":[],"size":40},"strategy_u_plus":{"x":-300,"source":"https://github.com/26F-Studio/Techmino/tree/main/parts/modes/strategy_u_plus.lua","name":"strategy_u_plus","y":-1380,"icon":"master","shape":2,"unlock":[],"size":30},"strategy_e":{"x":-150,"source":"https://github.com/26F-Studio/Techmino/tree/main/parts/modes/strategy_e.lua","name":"strategy_e","y":-1020,"icon":"master","shape":3,"unlock":["strategy_e_plus"],"size":40},"strategy_h":{"x":-150,"source":"https://github.com/26F-Studio/Techmino/tree/main/parts/modes/strategy_h.lua","name":"strategy_h","y":-1150,"icon":"master","shape":3,"unlock":["strategy_h_plus"],"size":35},"solo_e":{"x":-600,"source":"https://github.com/26F-Studio/Techmino/tree/main/parts/modes/solo_e.lua","name":"solo_e","y":-1000,"icon":"solo","shape":1,"unlock":["solo_n"],"size":40},"solo_h":{"x":-1000,"source":"https://github.com/26F-Studio/Techmino/tree/main/parts/modes/solo_h.lua","name":"solo_h","y":-1000,"icon":"solo","shape":1,"unlock":["solo_l","techmino49_e"],"size":40},"marathon_inf":{"x":-1000,"source":"https://github.com/26F-Studio/Techmino/tree/main/parts/modes/marathon_inf.lua","name":"marathon_inf","y":-400,"icon":"marathon","shape":1,"unlock":[],"size":40},"blind_u":{"x":150,"source":"https://github.com/26F-Studio/Techmino/tree/main/parts/modes/blind_u.lua","name":"blind_u","y":-1100,"icon":"hidden4","shape":3,"unlock":["blind_wtf"],"size":30},"stack_v1_20l":{"name":"stack_v1_20l","x":-1400,"y":600,"size":40,"shape":1,"icon":"mess","unlock":["stack_v1_40l"],"source":"https://github.com/26F-Studio/Techmino/blob/v0.16.0/parts/modes/stack_20l.lua"},"stack_v1_40l":{"name":"stack_v1_40l","x":-1250,"y":600,"size":40,"shape":1,"icon":"mess","unlock":["stack_v1_100l"],"source":"https://github.com/26F-Studio/Techmino/blob/v0.16.0/parts/modes/stack_40l.lua"},"stack_v1_100l":{"name":"stack_v1_100l","x":-1100,"y":600,"size":40,"shape":1,"icon":"mess","unlock":[],"source":"https://github.com/26F-Studio/Techmino/blob/v0.16.0/parts/modes/stack_100l.lua"},"stack_v2_e":{"name":"stack_v2_e","x":-1400,"y":750,"size":40,"shape":1,"icon":"mess","unlock":["stack_v2_h"],"source":"https://github.com/26F-Studio/Techmino/blob/v0.16.1/parts/modes/stack_e.lua"},"stack_v2_h":{"name":"stack_v2_h","x":-1250,"y":750,"size":40,"shape":3,"icon":"mess","unlock":["stack_v2_u"],"source":"https://github.com/26F-Studio/Techmino/blob/v0.16.1/parts/modes/stack_h.lua"},"stack_v2_u":{"name":"stack_v2_u","x":-1100,"y":750,"size":40,"shape":2,"icon":"mess","unlock":[],"source":"https://github.com/26F-Studio/Techmino/blob/v0.16.1/parts/modes/stack_u.lua"},"stack_v3_e":{"name":"stack_v3_e","x":-1400,"y":900,"size":40,"shape":1,"icon":"mess","unlock":["stack_v3_h"],"source":"https://github.com/26F-Studio/Techmino/blob/v0.16.4/parts/modes/stack_e.lua"},"stack_v3_h":{"name":"stack_v3_h","x":-1250,"y":900,"size":40,"shape":3,"icon":"mess","unlock":["stack_v3_u"],"source":"https://github.com/26F-Studio/Techmino/blob/v0.16.4/parts/modes/stack_h.lua"},"stack_v3_u":{"name":"stack_v3_u","x":-1100,"y":900,"size":40,"shape":2,"icon":"mess","unlock":[],"source":"https://github.com/26F-Studio/Techmino/blob/v0.16.4/parts/modes/stack_u.lua"},"stack_v4_e":{"name":"stack_v4_e","x":-1400,"y":1050,"size":40,"shape":1,"icon":"mess","unlock":["stack_v4_u"],"source":"https://github.com/26F-Studio/Techmino/blob/v0.17.4/parts/modes/stack_e.lua"},"stack_v4_u":{"name":"stack_v4_u","x":-1100,"y":1050,"size":40,"shape":3,"icon":"mess","unlock":[],"source":"https://github.com/26F-Studio/Techmino/blob/v0.17.4/parts/modes/stack_u.lua"},"stack_e":{"name":"stack_e","x":-1400,"y":1200,"size":40,"shape":1,"icon":"mess","unlock":["stack_u"],"source":"https://github.com/26F-Studio/Techmino/blob/main/parts/modes/stack_e.lua"},"stack_u":{"name":"stack_u","x":-1100,"y":1200,"size":40,"shape":3,"icon":"mess","unlock":[],"source":"https://github.com/26F-Studio/Techmino/blob/main/parts/modes/stack_e.lua"},"rhythm_e":{"name":"rhythm_e","x":-900,"y":600,"size":40,"shape":1,"icon":"rhythm","unlock":["rhythm_h"],"source":"https://github.com/26F-Studio/Techmino/blob/v0.16.4/parts/modes/rhythm_e.lua"},"rhythm_h":{"name":"rhythm_h","x":-750,"y":600,"size":40,"shape":3,"icon":"rhythm","unlock":["rhythm_u"],"source":"https://github.com/26F-Studio/Techmino/blob/v0.16.4/parts/modes/rhythm_h.lua"},"rhythm_u":{"name":"rhythm_u","x":-600,"y":600,"size":40,"shape":2,"icon":"rhythm","unlock":[],"source":"https://github.com/26F-Studio/Techmino/blob/v0.16.4/parts/modes/rhythm_u.lua"},"tech_finesse_lock":{"name":"tech_finesse_lock","x":-400,"y":600,"size":40,"shape":1,"icon":"tech","unlock":["tech_finesse_lock_f"],"source":"https://github.com/26F-Studio/Techmino/blob/v0.17.15/parts/modes/tech_finesse_lock.lua"},"tech_finesse_lock_f":{"name":"tech_finesse_lock_f","x":-250,"y":600,"size":40,"shape":3,"icon":"tech_plus","unlock":[],"source":"https://github.com/26F-Studio/Techmino/blob/v0.17.15/parts/modes/tech_finesse_lock_f.lua"},"techrash_n":{"name":"techrash_n","x":-50,"y":600,"size":40,"shape":3,"icon":"drought","unlock":["techrash_u"],"source":"https://github.com/26F-Studio/Techmino/blob/main/parts/modes/techrash_n.lua"},"techrash_u":{"name":"techrash_u","x":100,"y":600,"size":40,"shape":2,"icon":"drought","unlock":[],"source":"https://github.com/26F-Studio/Techmino/blob/main/parts/modes/techrash_u.lua"},"marathon_bfmax":{"name":"marathon_bfmax","x":500,"y":600,"size":40,"shape":1,"icon":"marathon","unlock":[],"source":"https://github.com/26F-Studio/Techmino/blob/main/parts/modes/marathon_bfmax.lua"},"classic_n":{"name":"classic_n","x":700,"y":600,"size":40,"shape":1,"icon":"classic","unlock":[],"source":"https://github.com/26F-Studio/Techmino/blob/30ed4179d68266e307c5a7d3a1e65ee8a2c612f2/parts/modes/classic_n.lua"},"sprintLock":{"name":"sprintLock","x":900,"y":600,"size":40,"shape":3,"icon":"sprint1","unlock":[],"source":"https://github.com/26F-Studio/Techmino/blob/main/parts/modes/sprintLock.lua"},"sprintSym":{"name":"sprintSym","x":1100,"y":600,"size":40,"shape":2,"icon":"sprint1","unlock":[],"source":"https://github.com/26F-Studio/Techmino/blob/main/parts/modes/sprintSym.lua"},"sprintFix":{"name":"sprintFix","x":900,"y":750,"size":40,"shape":3,"icon":"sprint1","unlock":[],"source":"https://github.com/26F-Studio/Techmino/blob/main/parts/modes/sprintFix.lua"},"sprintMD":{"name":"sprintMD","x":1100,"y":750,"size":40,"shape":2,"icon":"sprint1","unlock":[],"source":"https://github.com/26F-Studio/Techmino/blob/main/parts/modes/sprintMD.lua"},"sprintSmooth":{"name":"sprintSmooth","x":900,"y":900,"size":40,"shape":3,"icon":"sprint1","unlock":[],"source":"https://github.com/26F-Studio/Techmino/blob/main/parts/modes/sprintSmooth.lua"},"master_death":{"name":"master_death","x":900,"y":1200,"size":40,"shape":3,"icon":"master","unlock":["master_phantom"],"source":"https://github.com/Another-Soul/Techmino-Unofficial-Expansion/blob/main/parts/modes/master_death.lua"},"master_phantom":{"name":"master_phantom","x":1100,"y":1200,"size":40,"shape":2,"icon":"master","unlock":[],"source":"https://github.com/Another-Soul/Techmino-Unofficial-Expansion/blob/main/parts/modes/master_phantom.lua"}},"starting_mode":"sprint_10l","min_x":-1470,"min_y":-1870,"max_x":1320,"max_y":1270}